odoo10_addon_sale_delivery_rate-10.0.1.1.0-py2.7-nspkg.pth
odoo/addons/sale_delivery_rate/README.rst
odoo/addons/sale_delivery_rate/__init__.py
odoo/addons/sale_delivery_rate/__manifest__.py
odoo/addons/sale_delivery_rate/demo/delivery_carrier.xml
odoo/addons/sale_delivery_rate/demo/delivery_carrier_rate.xml
odoo/addons/sale_delivery_rate/demo/product_product.xml
odoo/addons/sale_delivery_rate/demo/product_template.xml
odoo/addons/sale_delivery_rate/demo/res_partner.xml
odoo/addons/sale_delivery_rate/demo/sale_order.xml
odoo/addons/sale_delivery_rate/demo/sale_order_line.xml
odoo/addons/sale_delivery_rate/demo/stock_picking.xml
odoo/addons/sale_delivery_rate/demo/stock_picking_rate.xml
odoo/addons/sale_delivery_rate/i18n/am.po
odoo/addons/sale_delivery_rate/i18n/ar.po
odoo/addons/sale_delivery_rate/i18n/bg.po
odoo/addons/sale_delivery_rate/i18n/bs.po
odoo/addons/sale_delivery_rate/i18n/ca.po
odoo/addons/sale_delivery_rate/i18n/cs.po
odoo/addons/sale_delivery_rate/i18n/cs_CZ.po
odoo/addons/sale_delivery_rate/i18n/da.po
odoo/addons/sale_delivery_rate/i18n/de.po
odoo/addons/sale_delivery_rate/i18n/el_GR.po
odoo/addons/sale_delivery_rate/i18n/en_GB.po
odoo/addons/sale_delivery_rate/i18n/es.po
odoo/addons/sale_delivery_rate/i18n/es_AR.po
odoo/addons/sale_delivery_rate/i18n/es_CL.po
odoo/addons/sale_delivery_rate/i18n/es_CO.po
odoo/addons/sale_delivery_rate/i18n/es_CR.po
odoo/addons/sale_delivery_rate/i18n/es_DO.po
odoo/addons/sale_delivery_rate/i18n/es_EC.po
odoo/addons/sale_delivery_rate/i18n/es_ES.po
odoo/addons/sale_delivery_rate/i18n/es_MX.po
odoo/addons/sale_delivery_rate/i18n/es_PE.po
odoo/addons/sale_delivery_rate/i18n/es_PY.po
odoo/addons/sale_delivery_rate/i18n/es_VE.po
odoo/addons/sale_delivery_rate/i18n/et.po
odoo/addons/sale_delivery_rate/i18n/eu.po
odoo/addons/sale_delivery_rate/i18n/eu_ES.po
odoo/addons/sale_delivery_rate/i18n/fa.po
odoo/addons/sale_delivery_rate/i18n/fi.po
odoo/addons/sale_delivery_rate/i18n/fr.po
odoo10_addon_sale_delivery_rate-10.0.1.1.0.dist-info/METADATA
odoo10_addon_sale_delivery_rate-10.0.1.1.0.dist-info/RECORD
odoo10_addon_sale_delivery_rate-10.0.1.1.0.dist-info/WHEEL
odoo10_addon_sale_delivery_rate-10.0.1.1.0.dist-info/namespace_packages.txt
odoo10_addon_sale_delivery_rate-10.0.1.1.0.dist-info/top_level.txt
