Metadata-Version: 2.1
Name: odoo10-addon-sale-delivery-rate
Version: 10.0.1.1.0
Summary: Extends notion of delivery carrier rate quotes to sale orders
Home-page: https://laslabs.com/
Author: LasLabs, Odoo Community Association (OCA)
Author-email: support@odoo-community.org
License: LGPL-3
Platform: UNKNOWN
Classifier: Programming Language :: Python
Classifier: Framework :: Odoo
Classifier: License :: OSI Approved :: GNU Lesser General Public License v3 (LGPLv3)
Requires-Python: ~=2.7
Requires-Dist: odoo10-addon-stock-picking-delivery-rate
Requires-Dist: odoo (<10.1dev,>=10.0)
